python_base_app
