Metadata-Version: 2.4
Name: python_base_app
Version: 0.3.6
Summary: Generic tools and base classes for Python applications with web interface.
Home-page: https://github.com/marcus67/python_base_app
Author: Marcus Rickert
Author-email: marcus.rickert@web.de
Requires-Python: >=3.10, <3.14
License-File: LICENSE
Requires-Dist: flask-wtf==1.2.2
Requires-Dist: flask==2.3.3
Requires-Dist: jinja2==3.1.5
Requires-Dist: markupSafe==2.1.5
Requires-Dist: wtforms==3.0.1
Requires-Dist: coverage==7.3.2
Requires-Dist: flask-login==0.6.3
Requires-Dist: psutil==7.2.0
Requires-Dist: pyjwt==2.10.1
Requires-Dist: pytest==9.0.2
Requires-Dist: python-dateutil==2.8.2
Requires-Dist: python-google-speak==0.2.2
Requires-Dist: requests==2.32.5
Requires-Dist: secure==2.0.0
Requires-Dist: setuptools==80.9.0
Requires-Dist: some_flask_helpers~=0.2.10
Requires-Dist: urllib3==2.6.2
Requires-Dist: werkzeug==3.1.4
Dynamic: author
Dynamic: author-email
Dynamic: description
Dynamic: description-content-type
Dynamic: home-page
Dynamic: license-file
Dynamic: requires-dist
Dynamic: requires-python
Dynamic: summary
